track_tools/__init__.py
track_tools/region_of_interest.py
track_tools/results_folder.py
track_tools/tracking_parameters.py
track_tools/cli/__init__.py
track_tools/cli/drift_correction.py
track_tools/cli/extract_trajectories.py
track_tools-0.1.0.dist-info/METADATA
track_tools-0.1.0.dist-info/WHEEL
track_tools-0.1.0.dist-info/entry_points.txt
track_tools-0.1.0.dist-info/top_level.txt
track_tools-0.1.0.dist-info/RECORD
